graphql/__init__.py
graphql/graphql.py
graphql/py.typed
graphql/version.py
graphql/error/__init__.py
graphql/error/graphql_error.py
graphql/error/located_error.py
graphql/error/syntax_error.py
graphql/execution/__init__.py
graphql/execution/collect_fields.py
graphql/execution/execute.py
graphql/execution/map_async_iterator.py
graphql/execution/middleware.py
graphql/execution/subscribe.py
graphql/execution/values.py
graphql/language/__init__.py
graphql/language/ast.py
graphql/language/block_string.py
graphql/language/character_classes.py
graphql/language/directive_locations.py
graphql/language/lexer.py
graphql/language/location.py
graphql/language/parser.py
graphql/language/predicates.py
graphql/language/print_location.py
graphql/language/print_string.py
graphql/language/printer.py
graphql/language/source.py
graphql/language/token_kind.py
graphql/language/visitor.py
graphql/pyutils/__init__.py
graphql/pyutils/awaitable_or_value.py
graphql/pyutils/cached_property.py
graphql/pyutils/convert_case.py
graphql/pyutils/description.py
graphql/pyutils/did_you_mean.py
graphql/pyutils/frozen_dict.py
graphql/pyutils/frozen_error.py
graphql/pyutils/frozen_list.py
graphql/pyutils/group_by.py
graphql/pyutils/identity_func.py
graphql/pyutils/inspect.py
graphql/pyutils/is_awaitable.py
graphql/pyutils/is_iterable.py
graphql/pyutils/merge_kwargs.py
graphql/pyutils/natural_compare.py
graphql/pyutils/path.py
graphql/pyutils/print_path_list.py
graphql/pyutils/simple_pub_sub.py
graphql/pyutils/suggestion_list.py
graphql/pyutils/undefined.py
graphql/subscription/__init__.py
graphql/type/__init__.py
graphql/type/assert_name.py
graphql/type/definition.py
graphql/type/directives.py
graphql/type/introspection.py
graphql/type/scalars.py
graphql/type/schema.py
graphql/type/validate.py
graphql/utilities/__init__.py
graphql/utilities/assert_valid_name.py
graphql/utilities/ast_from_value.py
graphql/utilities/ast_to_dict.py
graphql/utilities/build_ast_schema.py
graphql_core-3.2.4.dist-info/LICENSE
graphql_core-3.2.4.dist-info/METADATA
graphql_core-3.2.4.dist-info/WHEEL
graphql_core-3.2.4.dist-info/top_level.txt
graphql_core-3.2.4.dist-info/RECORD
