Metadata-Version: 2.1
Name: graphql-core
Version: 3.2.4
Summary: GraphQL implementation for Python, a port of GraphQL.js, the JavaScript reference implementation for GraphQL.
Home-page: https://github.com/graphql-python/graphql-core
Author: Christoph Zwerschke
Author-email: cito@online.de
License: MIT license
Keywords: graphql
Classifier: Development Status :: 5 - Production/Stable
Classifier: Intended Audience :: Developers
Classifier: Topic :: Software Development :: Libraries
Classifier: License :: OSI Approved :: MIT License
Classifier: Programming Language :: Python :: 3
Classifier: Programming Language :: Python :: 3 :: Only
Classifier: Programming Language :: Python :: 3.6
Classifier: Programming Language :: Python :: 3.7
Classifier: Programming Language :: Python :: 3.8
Classifier: Programming Language :: Python :: 3.9
Classifier: Programming Language :: Python :: 3.10
Requires-Python: >=3.6,<4
License-File: LICENSE
